interactions/ext/i18n/__init__.py
interactions/ext/i18n/base.py
interactions/ext/i18n/extension.py
interactions/ext/i18n/json_generator.py
interactions/ext/i18n/models.py
interactions/ext/i18n/utils.py
interactions_i18n-1.0.0.dist-info/LICENSE
interactions_i18n-1.0.0.dist-info/METADATA
interactions_i18n-1.0.0.dist-info/WHEEL
interactions_i18n-1.0.0.dist-info/top_level.txt
interactions_i18n-1.0.0.dist-info/RECORD
