Metadata-Version: 2.1
Name: interactions-i18n
Version: 1.0.0
Summary: Add localization support to your interactions.py bot
Home-page: https://github.com/Damego/interactions-i18n
Author: Damego
Author-email: damego.dev@gmail.com
License: MIT License
Classifier: Intended Audience :: Developers
Classifier: License :: OSI Approved :: MIT License
Classifier: Natural Language :: English
Classifier: Operating System :: OS Independent
Classifier: Programming Language :: Python :: 3
Classifier: Programming Language :: Python :: 3.8
Classifier: Programming Language :: Python :: 3.9
Classifier: Programming Language :: Python :: 3.10
Classifier: Topic :: Internet
Classifier: Topic :: Software Development :: Libraries :: Python Modules
Classifier: Topic :: Software Development :: Libraries
Classifier: Topic :: Utilities
Requires-Python: >=3.8.6
License-File: LICENSE
Requires-Dist: discord-py-interactions (>=4.3.2)
